heapx/__init__.py
heapx/_heapx.cpython-314-darwin.so
heapx/heapx.c
heapx-0.0.3.dist-info/licenses/LICENSE
heapx-0.0.3.dist-info/METADATA
heapx-0.0.3.dist-info/WHEEL
heapx-0.0.3.dist-info/top_level.txt
heapx-0.0.3.dist-info/RECORD
