Metadata-Version: 2.4
Name: heapx
Version: 0.0.3
Summary: Ultra-optimized heap operations with comprehensive functionality and superior performance
Home-page: https://github.com/ivan121500/heapx
Author: Aniruddha Mukherjee
Author-email: mukher66@purdue.edu
Project-URL: Homepage, https://github.com/ivan121500/heapx
Project-URL: Documentation, https://github.com/ivan121500/heapx
Project-URL: Repository, https://github.com/ivan121500/heapx
Project-URL: Changelog, https://github.com/ivan121500/heapx
Project-URL: Issues, https://github.com/ivan121500/heapx
Keywords: heap,priority-queue,optimized,algorithm,data-structures,performance,n-ary-heap,max-heap,min-heap
Platform: any
Classifier: Development Status :: 5 - Production/Stable
Classifier: Intended Audience :: Developers
Classifier: Intended Audience :: Science/Research
Classifier: License :: OSI Approved :: MIT License
Classifier: Operating System :: OS Independent
Classifier: Programming Language :: Python :: 3
Classifier: Programming Language :: Python :: 3.8
Classifier: Programming Language :: Python :: 3.9
Classifier: Programming Language :: Python :: 3.10
Classifier: Programming Language :: Python :: 3.11
Classifier: Programming Language :: Python :: 3.12
Classifier: Programming Language :: Python :: 3.13
Classifier: Programming Language :: Python :: 3.14
Classifier: Programming Language :: Python :: Implementation :: CPython
Classifier: Topic :: Software Development :: Libraries :: Python Modules
Classifier: Topic :: Scientific/Engineering
Classifier: Topic :: System :: Hardware
Classifier: Topic :: Utilities
Classifier: Typing :: Typed
Requires-Python: >=3.8
License-File: LICENSE
Provides-Extra: dev
Requires-Dist: pytest>=6.0; extra == "dev"
Requires-Dist: pytest-benchmark>=3.4; extra == "dev"
Requires-Dist: black>=22.0; extra == "dev"
Requires-Dist: isort>=5.0; extra == "dev"
Requires-Dist: mypy>=0.900; extra == "dev"
Requires-Dist: flake8>=4.0; extra == "dev"
Provides-Extra: test
Requires-Dist: pytest>=6.0; extra == "test"
Requires-Dist: pytest-benchmark>=3.4; extra == "test"
Provides-Extra: docs
Requires-Dist: sphinx>=4.0; extra == "docs"
Requires-Dist: sphinx-rtd-theme>=1.0; extra == "docs"
Dynamic: author
Dynamic: author-email
Dynamic: home-page
Dynamic: license-file
Dynamic: platform
Dynamic: requires-python
